{"udderly.tickets": {"hash": "w39plbu3i27evkdj0wcn", "name": "Udderly Tickets"}, "uden.at.prale.det.er.harry": {"hash": "co1w0z", "name": "Uden at prale - det er Harry"}, "udodge.practice.tool": {"hash": "e8p6ljmjfja8j1b1vmpl", "name": "uDodge:Practice Tool"}, "udongein.x": {"hash": "co3vh9", "name": "Udongein X"}, "udraw.marvel.super.hero.squad.comic.combat": {"hash": "co4861", "name": "uDraw Marvel Super Hero Squad: Comic Combat"}, "udraw.pictionary": {"hash": "co48ue", "name": "uDraw Pictionary"}, "udraw.studio": {"hash": "n0c7mq0g09q70lptzrhc", "name": "uDraw Studio"}, "udraw.studio.instant.artist": {"hash": "co25k5", "name": "uDraw Studio: Instant Artist"}}