{"00.mem.le.chat": {"hash": "lmhelexfhlh3ovoj9ji0", "name": "00 mem.: ~Le Chat~"}, "0000": {"hash": "co3kqg", "name": "0000"}, "000000ff0000": {"hash": "co4oql", "name": "000000FF0000"}, "0008.the.story": {"hash": "rnabzgvkx3mgknjroogy", "name": "0008 The Story"}, "001.earth": {"hash": "co4gh7", "name": "001 Earth"}, "005": {"hash": "hxhhtnsi9haoocmtnnib", "name": "005"}, "007.legends": {"hash": "co203u", "name": "007 Legends"}, "007.legends.eve": {"hash": "t6aehfi84q4dlp6rsxwc", "name": "007 Legends: Eve"}, "007.legends.patrice": {"hash": "co1ybg", "name": "007 Legends: Patrice"}, "007.legends.skyfall": {"hash": "co2e8p", "name": "007 Legends: Skyfall"}, "007.quantum.of.solace": {"hash": "co3ega", "name": "007: Quantum of Solace"}, "007.racing": {"hash": "co3dup", "name": "007 Racing"}}