{"eba.egg.a.hatch.trip": {"hash": "co24h0", "name": "Eba & Egg: A Hatch Trip"}, "eball": {"hash": "co1l2c", "name": "eBall"}, "ebanbashi.kaiwa": {"hash": "co4ll6", "name": "Ebanbashi: Kaiwa"}, "ebaseball.powerful.pro.yakyuu.2020": {"hash": "co2ya4", "name": "eBaseball Powerful Pro Yakyuu 2020"}, "ebaseball.powerful.pro.yakyuu.2022": {"hash": "co4ohx", "name": "eBaseball Powerful Pro Yakyuu 2022"}, "ebaseball.professional.yakyuu.spirits.2021.grand.slam": {"hash": "co39zd", "name": "eBaseball Professional Yakyuu Spirits 2021: Grand Slam"}, "ebe": {"hash": "co3u05", "name": "EBE"}, "eberouge": {"hash": "co3uvq", "name": "Eberouge"}, "eberouge.2": {"hash": "co3uvt", "name": "Eberouge 2"}, "eberouge.special.koi.to.mahou.no.gakuen.seikatsu": {"hash": "co3uvr", "name": "Eberouge Special: Koi to Mahou no Gakuen Seikatsu"}, "ebikore.amagami": {"hash": "co4o7e", "name": "EbiKore+ Amagami"}, "ebola.2": {"hash": "co2ohr", "name": "EBOLA 2"}, "ebola.2.survival": {"hash": "co3prh", "name": "Ebola 2 Survival"}, "ebonside": {"hash": "co4fbr", "name": "EbonSide"}, "ebonstar": {"hash": "lqfvoauwanftr6ur2o2m", "name": "Ebonstar"}, "ebony": {"hash": "co3pri", "name": "EBONY"}, "ebony.spire.heresy": {"hash": "co24h1", "name": "Ebony Spire: Heresy"}, "ebuc": {"hash": "jepxox6cy5i6nfimonkq", "name": "Ebuc"}, "ebullition.lbvr": {"hash": "co3prj", "name": "Ebullition LBVR"}}