{"ic.carddass.dragonball": {"hash": "u6ngwd2puhy5qn4geuhe", "name": "IC Carddass DragonBall"}, "ican": {"hash": "co1rz0", "name": "Ican"}, "icarly": {"hash": "co319k", "name": "iCarly"}, "icarly.2.ijoin.the.click": {"hash": "co2sn7", "name": "iCarly 2: iJoin the Click"}, "icarly.gibby.pinball": {"hash": "co2ma6", "name": "iCarly: Gibby Pinball"}, "icarly.groovie.foodie": {"hash": "y6vogdhvnisbcml5fq0j", "name": "iCarly: Groovie Foodie!"}, "icarus": {"hash": "co4gv6", "name": "Icarus"}, "icarus.alien.vanguard": {"hash": "co4mce", "name": "Icarus: Alien Vanguard"}, "icarus.needs": {"hash": "co3wz1", "name": "Icarus Needs"}, "icarus.online": {"hash": "co2qe3", "name": "Icarus Online"}, "icarus.proudbottom.in.the.curse.of.the.chocolate.fountain": {"hash": "dtb9b9nyxf6lzno2osfh", "name": "Icarus Proudbottom in The Curse of the Chocolate Fountain"}, "icarus.proudbottom.s.world.of.typing.weekly": {"hash": "d5wbulm39xklxwhfkq3v", "name": "Icarus Proudbottom's World of Typing Weekly!"}, "icarus.proudbottom.teaches.typing": {"hash": "t6n0bxme8d3ncyknuusn", "name": "Icarus Proudbottom Teaches Typing"}, "icarus.sanctuary.of.the.gods": {"hash": "co2xhd", "name": "Icarus: Sanctuary of the Gods"}, "icarus.six.sixty.six": {"hash": "wafblor9uw0jkgbq9jab", "name": "Icarus Six Sixty Six"}, "icarus.starship.command.simulator": {"hash": "co2bog", "name": "Icarus Starship Command Simulator"}, "icarus.styx.map.pack": {"hash": "co4v4g", "name": "Icarus: Styx Map Pack"}, "icarus.the.day.4": {"hash": "idxva6kuskmitd5kra8i", "name": "Icarus: The Day 4"}, "icbm": {"hash": "co2qe4", "name": "ICBM"}, "ice.age": {"hash": "co2d1b", "name": "Ice Age"}, "ice.age.2.the.meltdown": {"hash": "co2d1a", "name": "Ice Age 2: The Meltdown"}, "ice.age.adventures": {"hash": "co4udv", "name": "Ice Age Adventures"}, "ice.age.arctic.blast": {"hash": "ncatdkg7ruonlgyukln0", "name": "Ice Age: Arctic Blast"}, "ice.age.continental.drift.arctic.games": {"hash": "co2ddm", "name": "Ice Age: Continental Drift \u2013 Arctic Games"}, "ice.age.dawn.of.the.dinosaurs": {"hash": "co2ddn", "name": "Ice Age: Dawn of the Dinosaurs"}, "ice.age.scrat.s.nutty.adventure": {"hash": "co24cs", "name": "Ice Age: Scrat's Nutty Adventure"}, "ice.age.village": {"hash": "ucb6oiygpou0swcfstai", "name": "Ice Age Village"}, "ice.and.fire": {"hash": "co3uqs", "name": "Ice and Fire"}, "ice.and.fire.of.maiden": {"hash": "co43gf", "name": "Ice and Fire of Maiden"}, "ice.and.fire.the.wizards": {"hash": "yhpwevqz7jahwnwtnubm", "name": "Ice and Fire: The Wizards"}, "ice.block": {"hash": "p6zc4rktjjaip46ybh6r", "name": "Ice Block"}, "ice.climber": {"hash": "co42t4", "name": "Ice Climber"}, "ice.climber.e": {"hash": "co438l", "name": "Ice Climber-e"}, "ice.cold.beer": {"hash": "ejtltuzdbyenuopoxwjj", "name": "Ice Cold Beer"}, "ice.cream.break": {"hash": "co4dpn", "name": "Ice Cream Break"}, "ice.cream.break.head.to.head": {"hash": "co4kf2", "name": "Ice Cream Break: Head to Head"}, "ice.cream.stall": {"hash": "tvl4swznpa0k6b3o0wg6", "name": "Ice Cream Stall"}, "ice.cream.surfer": {"hash": "co4hn4", "name": "Ice Cream Surfer"}, "ice.cream.truck": {"hash": "co43gh", "name": "Ice Cream Truck"}, "ice.crystal.labyrinth": {"hash": "bohwnnkfnbsfqddveikf", "name": "Ice Crystal Labyrinth"}, "ice.demon": {"hash": "co43gi", "name": "Ice Demon"}, "ice.driver": {"hash": "co28px", "name": "Ice Driver"}, "ice.fever": {"hash": "lick0zehzaosbjgmj1k0", "name": "Ice Fever"}, "ice.hockey": {"hash": "pnytoyebtn5nc0pijavp", "name": "Ice Hockey"}, "ice.hockey.slovakia.2011": {"hash": "se0hya6ismpsnv4pmhhi", "name": "Ice Hockey Slovakia 2011"}, "ice.hunter": {"hash": "norkmvgzujuhb1ytroqy", "name": "Ice Hunter"}, "ice.lakes": {"hash": "co1r27", "name": "Ice Lakes"}, "ice.nine": {"hash": "co3gvu", "name": "Ice Nine"}, "ice.princess.mermaid.salon.girls.makeover.games": {"hash": "i7opvvxdqh2yfdmnofw5", "name": "Ice Princess Mermaid Salon: Girls Makeover Games"}, "ice.queen.salon.girls.makeup.and.dressup.game": {"hash": "x5ge6fwmf2rophhtwjja", "name": "Ice Queen Salon - Girls Makeup and Dressup Game"}, "ice.queen.wedding.salon.frost.bridal.game": {"hash": "akob8rjd1tytpiyjislz", "name": "Ice Queen Wedding Salon: Frost Bridal Game"}, "ice.rage": {"hash": "izd9buojccocxzaqxhcr", "name": "Ice Rage"}, "ice.skating.ballerina": {"hash": "ktopmrlis0jg8vtg8haq", "name": "Ice Skating Ballerina"}, "ice.star": {"hash": "co43gk", "name": "Ice Star"}, "ice.star.chapter.2": {"hash": "co3syk", "name": "Ice star: Chapter 2"}, "ice.star.tribes": {"hash": "co43gm", "name": "Ice Star Tribes"}, "ice.station.z": {"hash": "co4rs7", "name": "Ice Station Z"}, "ice.sugar": {"hash": "co4f7z", "name": "Ice sugar"}, "ice.temple": {"hash": "co2ys6", "name": "ICE Temple"}, "ice.trek": {"hash": "co1pit", "name": "Ice Trek"}, "icebergs": {"hash": "co47tz", "name": "Icebergs"}, "icebound": {"hash": "co43gg", "name": "Icebound"}, "icebox": {"hash": "l5hj6gewn8cduud8jgd1", "name": "Icebox"}, "icebox.speedgunner": {"hash": "co24wb", "name": "ICEBOX: Speedgunner"}, "icebreaker": {"hash": "co1p59", "name": "Icebreaker"}, "icebreaker.a.viking.voyage": {"hash": "fxkpjwqtxmrr5spwd3zr", "name": "Icebreaker: A Viking Voyage"}, "icebreaker.the.text.adventure": {"hash": "f5nik0bfwgee05fx3qrn", "name": "Icebreaker: The Text Adventure"}, "icebreakers": {"hash": "zsjaoo0xnjsvdvaflcxb", "name": "Icebreakers"}, "iced": {"hash": "co24wa", "name": "ICED"}, "icee.maker": {"hash": "co3h7k", "name": "Icee Maker"}, "iceman.digital.playstage": {"hash": "co489c", "name": "Iceman: Digital PlayStage"}, "icemaze.cave.skate.escape": {"hash": "co4lul", "name": "Icemaze Cave: Skate Escape"}, "iceroyds": {"hash": "co43gj", "name": "Iceroyds!"}, "icesolation": {"hash": "co4cg2", "name": "Icesolation"}, "icewall": {"hash": "co4f45", "name": "Icewall"}, "icewind.dale": {"hash": "co1t8h", "name": "Icewind Dale"}, "icewind.dale.3.in.1.compilation": {"hash": "co2stx", "name": "Icewind Dale 3-in-1 Compilation"}, "icewind.dale.enhanced.edition": {"hash": "co1t8i", "name": "Icewind Dale: Enhanced Edition"}, "icewind.dale.heart.of.winter": {"hash": "co1t8l", "name": "Icewind Dale: Heart of Winter"}, "icewind.dale.ii": {"hash": "co1t8o", "name": "Icewind Dale II"}, "icewind.dale.ii.adventure.pack": {"hash": "co1t8y", "name": "Icewind Dale II: Adventure Pack"}, "icewind.dale.trials.of.the.luremaster": {"hash": "co1t8s", "name": "Icewind Dale: Trials of the Luremaster"}, "icewords": {"hash": "co4b3p", "name": "Icewords"}, "icey": {"hash": "co24w8", "name": "ICEY"}, "ichi": {"hash": "oci2u0ui01qdfbbtzf76", "name": "Ichi"}, "ichigeki.hagane.no.hito": {"hash": "co3xue", "name": "Ichigeki: Hagane No Hito"}, "ichigeki.nyuukon.panda.ball": {"hash": "co4wqx", "name": "Ichigeki Nyuukon! Panda Ball"}, "ichigeki.sacchu.hoihoi.san": {"hash": "mtrl7xnh4la22ca361pi", "name": "Ichigeki Sacchu!! HoiHoi-san"}, "ichigo.100": {"hash": "yx8mmsyqgovpmdob4uml", "name": "Ichigo 100%"}, "ichiro.shounen.kitan": {"hash": "co31ob", "name": "Ichiro Shounen Kitan"}, "ichor": {"hash": "co43gl", "name": "Ichor"}, "ichth.ys": {"hash": "co43gn", "name": "Ichth.ys"}, "ico": {"hash": "co4dg2", "name": "ICO"}, "ico.shadow.of.the.colossus.collection": {"hash": "co4ako", "name": "ICO & Shadow Of The Colossus Collection"}, "icon.jon": {"hash": "z6fqy47hhltraltm7qyi", "name": "Icon Jon"}, "icon.quest.for.the.ring": {"hash": "qtdgnsrhye5u1if5chst", "name": "ICON: Quest for the Ring"}, "iconic": {"hash": "co43go", "name": "Iconic"}, "iconoclasts": {"hash": "co2ug9", "name": "Iconoclasts"}, "icons.combat.arena": {"hash": "co2a7k", "name": "Icons: Combat Arena"}, "icorp": {"hash": "co43gp", "name": "iCorp"}, "icy": {"hash": "co2qe5", "name": "Icy"}, "icy.frostbite.edition": {"hash": "co219z", "name": "ICY: Frostbite Edition"}, "icy.maze": {"hash": "co2wzu", "name": "Icy Maze"}, "icy.ropes": {"hash": "jpj5r1tcoulca5qnovyu", "name": "Icy Ropes"}, "icy.tower": {"hash": "co1umk", "name": "Icy Tower"}, "icycle.on.thin.ice": {"hash": "co24w7", "name": "Icycle: On Thin Ice"}}